{
  "meta": {
    "title": "Clair de Lune",
    "bpm": 60,
    "songLengthMs": 322500
  },
  "notes": [
    {
      "id": "n1",
      "time": 500,
      "x": 3,
      "type": "hold",
      "durationMs": 3880
    },
    {
      "id": "n2",
      "time": 1000,
      "x": 7,
      "type": "hold",
      "durationMs": 2000
    },
    {
      "id": "n3",
      "time": 3000,
      "x": 6,
      "type": "hold",
      "durationMs": 1880
    },
    {
      "id": "n4",
      "time": 4500,
      "x": 3,
      "type": "hold",
      "durationMs": 4380
    },
    {
      "id": "n5",
      "time": 5000,
      "x": 6,
      "type": "tap"
    },
    {
      "id": "n6",
      "time": 5500,
      "x": 6,
      "type": "tap"
    },
    {
      "id": "n7",
      "time": 6000,
      "x": 6,
      "type": "hold",
      "durationMs": 3500
    },
    {
      "id": "n8",
      "time": 9000,
      "x": 3,
      "type": "hold",
      "durationMs": 4500
    },
    {
      "id": "n9",
      "time": 9500,
      "x": 5,
      "type": "tap"
    },
    {
      "id": "n10",
      "time": 10000,
      "x": 6,
      "type": "tap"
    },
    {
      "id": "n11",
      "time": 10500,
      "x": 5,
      "type": "hold",
      "durationMs": 3380
    },
    {
      "id": "n12",
      "time": 11250,
      "x": 7,
      "type": "hold",
      "durationMs": 1500
    },
    {
      "id": "n13",
      "time": 12750,
      "x": 6,
      "type": "hold",
      "durationMs": 1250
    },
    {
      "id": "n14",
      "time": 13500,
      "x": 2,
      "type": "hold",
      "durationMs": 4380
    },
    {
      "id": "n15",
      "time": 14000,
      "x": 5,
      "type": "tap"
    },
    {
      "id": "n16",
      "time": 14500,
      "x": 5,
      "type": "tap"
    },
    {
      "id": "n17",
      "time": 15000,
      "x": 5,
      "type": "hold",
      "durationMs": 2880
    },
    {
      "id": "n18",
      "time": 18000,
      "x": 2,
      "type": "hold",
      "durationMs": 2880
    },
    {
      "id": "n19",
      "time": 18000,
      "x": 5,
      "type": "tap"
    },
    {
      "id": "n20",
      "time": 18500,
      "x": 5,
      "type": "tap"
    },
    {
      "id": "n21",
      "time": 19000,
      "x": 6,
      "type": "tap"
    },
    {
      "id": "n22",
      "time": 19500,
      "x": 5,
      "type": "tap"
    },
    {
      "id": "n23",
      "time": 20000,
      "x": 6,
      "type": "tap"
    },
    {
      "id": "n24",
      "time": 20500,
      "x": 5,
      "type": "tap"
    },
    {
      "id": "n25",
      "time": 21000,
      "x": 2,
      "type": "hold",
      "durationMs": 1380
    },
    {
      "id": "n26",
      "time": 21000,
      "x": 5,
      "type": "tap"
    },
    {
      "id": "n27",
      "time": 21500,
      "x": 5,
      "type": "tap"
    },
    {
      "id": "n28",
      "time": 22000,
      "x": 5,
      "type": "tap"
    },
    {
      "id": "n29",
      "time": 22500,
      "x": 2,
      "type": "hold",
      "durationMs": 2880
    },
    {
      "id": "n30",
      "time": 22500,
      "x": 4,
      "type": "hold",
      "durationMs": 2880
    },
    {
      "id": "n31",
      "time": 23000,
      "x": 5,
      "type": "tap"
    },
    {
      "id": "n32",
      "time": 23500,
      "x": 5,
      "type": "tap"
    },
    {
      "id": "n33",
      "time": 24000,
      "x": 5,
      "type": "hold",
      "durationMs": 1500
    },
    {
      "id": "n34",
      "time": 25500,
      "x": 2,
      "type": "hold",
      "durationMs": 1500
    },
    {
      "id": "n35",
      "time": 25500,
      "x": 4,
      "type": "hold",
      "durationMs": 1380
    },
    {
      "id": "n36",
      "time": 27000,
      "x": 1,
      "type": "hold",
      "durationMs": 2880
    },
    {
      "id": "n37",
      "time": 27000,
      "x": 4,
      "type": "tap"
    },
    {
      "id": "n38",
      "time": 27500,
      "x": 4,
      "type": "tap"
    },
    {
      "id": "n39",
      "time": 28000,
      "x": 5,
      "type": "tap"
    },
    {
      "id": "n40",
      "time": 28500,
      "x": 4,
      "type": "tap"
    },
    {
      "id": "n41",
      "time": 29000,
      "x": 5,
      "type": "tap"
    },
    {
      "id": "n42",
      "time": 29500,
      "x": 4,
      "type": "tap"
    },
    {
      "id": "n43",
      "time": 30000,
      "x": 1,
      "type": "hold",
      "durationMs": 1380
    },
    {
      "id": "n44",
      "time": 30000,
      "x": 4,
      "type": "tap"
    },
    {
      "id": "n45",
      "time": 30500,
      "x": 4,
      "type": "tap"
    },
    {
      "id": "n46",
      "time": 31000,
      "x": 4,
      "type": "tap"
    },
    {
      "id": "n47",
      "time": 31500,
      "x": 1,
      "type": "hold",
      "durationMs": 2880
    },
    {
      "id": "n48",
      "time": 31500,
      "x": 4,
      "type": "tap"
    },
    {
      "id": "n49",
      "time": 32000,
      "x": 4,
      "type": "tap"
    },
    {
      "id": "n50",
      "time": 32500,
      "x": 4,
      "type": "tap"
    },
    {
      "id": "n51",
      "time": 33000,
      "x": 4,
      "type": "hold",
      "durationMs": 1380
    },
    {
      "id": "n52",
      "time": 34500,
      "x": 1,
      "type": "tap"
    },
    {
      "id": "n53",
      "time": 34500,
      "x": 4,
      "type": "hold",
      "durationMs": 1500
    },
    {
      "id": "n54",
      "time": 35250,
      "x": 0,
      "type": "tap"
    },
    {
      "id": "n55",
      "time": 36000,
      "x": 0,
      "type": "tap"
    },
    {
      "id": "n56",
      "time": 36500,
      "x": 4,
      "type": "hold",
      "durationMs": 1000
    },
    {
      "id": "n57",
      "time": 37000,
      "x": 3,
      "type": "hold",
      "durationMs": 3500
    },
    {
      "id": "n58",
      "time": 37500,
      "x": 7,
      "type": "hold",
      "durationMs": 1500
    },
    {
      "id": "n59",
      "time": 39000,
      "x": 6,
      "type": "hold",
      "durationMs": 2000
    },
    {
      "id": "n60",
      "time": 40500,
      "x": 0,
      "type": "hold",
      "durationMs": 3000
    },
    {
      "id": "n61",
      "time": 41000,
      "x": 1,
      "type": "hold",
      "durationMs": 4000
    },
    {
      "id": "n62",
      "time": 41000,
      "x": 5,
      "type": "hold",
      "durationMs": 4000
    },
    {
      "id": "n63",
      "time": 41500,
      "x": 7,
      "type": "tap"
    },
    {
      "id": "n64",
      "time": 42000,
      "x": 6,
      "type": "hold",
      "durationMs": 3500
    },
    {
      "id": "n65",
      "time": 45000,
      "x": 0,
      "type": "hold",
      "durationMs": 3000
    },
    {
      "id": "n66",
      "time": 45500,
      "x": 1,
      "type": "hold",
      "durationMs": 1000
    },
    {
      "id": "n67",
      "time": 45500,
      "x": 4,
      "type": "tap"
    },
    {
      "id": "n68",
      "time": 46000,
      "x": 4,
      "type": "tap"
    },
    {
      "id": "n69",
      "time": 46500,
      "x": 2,
      "type": "hold",
      "durationMs": 1500
    },
    {
      "id": "n70",
      "time": 46500,
      "x": 5,
      "type": "hold",
      "durationMs": 1500
    },
    {
      "id": "n71",
      "time": 48000,
      "x": 1,
      "type": "hold",
      "durationMs": 1500
    },
    {
      "id": "n72",
      "time": 48000,
      "x": 4,
      "type": "hold",
      "durationMs": 1500
    },
    {
      "id": "n73",
      "time": 49500,
      "x": 0,
      "type": "hold",
      "durationMs": 3000
    },
    {
      "id": "n74",
      "time": 50000,
      "x": 1,
      "type": "hold",
      "durationMs": 4000
    },
    {
      "id": "n75",
      "time": 50000,
      "x": 5,
      "type": "hold",
      "durationMs": 4000
    },
    {
      "id": "n76",
      "time": 50500,
      "x": 7,
      "type": "tap"
    },
    {
      "id": "n77",
      "time": 51000,
      "x": 6,
      "type": "hold",
      "durationMs": 1380
    },
    {
      "id": "n78",
      "time": 52500,
      "x": 6,
      "type": "hold",
      "durationMs": 2000
    },
    {
      "id": "n79",
      "time": 54000,
      "x": 0,
      "type": "hold",
      "durationMs": 4380
    },
    {
      "id": "n80",
      "time": 54500,
      "x": 1,
      "type": "hold",
      "durationMs": 1000
    },
    {
      "id": "n81",
      "time": 54500,
      "x": 4,
      "type": "tap"
    },
    {
      "id": "n82",
      "time": 55000,
      "x": 4,
      "type": "tap"
    },
    {
      "id": "n83",
      "time": 55500,
      "x": 2,
      "type": "hold",
      "durationMs": 2000
    },
    {
      "id": "n84",
      "time": 55500,
      "x": 5,
      "type": "tap"
    },
    {
      "id": "n85",
      "time": 56250,
      "x": 5,
      "type": "hold",
      "durationMs": 1500
    },
    {
      "id": "n86",
      "time": 57750,
      "x": 4,
      "type": "tap"
    },
    {
      "id": "n87",
      "time": 58500,
      "x": 0,
      "type": "hold",
      "durationMs": 3000
    },
    {
      "id": "n88",
      "time": 58500,
      "x": 7,
      "type": "tap"
    },
    {
      "id": "n89",
      "time": 59000,
      "x": 1,
      "type": "hold",
      "durationMs": 4000
    },
    {
      "id": "n90",
      "time": 59000,
      "x": 4,
      "type": "hold",
      "durationMs": 4000
    },
    {
      "id": "n91",
      "time": 59500,
      "x": 7,
      "type": "tap"
    },
    {
      "id": "n92",
      "time": 60000,
      "x": 6,
      "type": "tap"
    },
    {
      "id": "n93",
      "time": 60750,
      "x": 2,
      "type": "hold",
      "durationMs": 2250
    },
    {
      "id": "n94",
      "time": 60750,
      "x": 6,
      "type": "hold",
      "durationMs": 1500
    },
    {
      "id": "n95",
      "time": 63000,
      "x": 0,
      "type": "hold",
      "durationMs": 3000
    },
    {
      "id": "n96",
      "time": 63750,
      "x": 3,
      "type": "hold",
      "durationMs": 1250
    },
    {
      "id": "n97",
      "time": 63750,
      "x": 7,
      "type": "hold",
      "durationMs": 1250
    },
    {
      "id": "n98",
      "time": 65000,
      "x": 2,
      "type": "tap"
    },
    {
      "id": "n99",
      "time": 65000,
      "x": 6,
      "type": "tap"
    },
    {
      "id": "n100",
      "time": 65500,
      "x": 2,
      "type": "tap"
    },
    {
      "id": "n101",
      "time": 65500,
      "x": 6,
      "type": "tap"
    },
    {
      "id": "n102",
      "time": 66000,
      "x": 2,
      "type": "tap"
    },
    {
      "id": "n103",
      "time": 66000,
      "x": 6,
      "type": "tap"
    },
    {
      "id": "n104",
      "time": 66500,
      "x": 2,
      "type": "tap"
    },
    {
      "id": "n105",
      "time": 66500,
      "x": 6,
      "type": "tap"
    },
    {
      "id": "n106",
      "time": 67000,
      "x": 2,
      "type": "tap"
    },
    {
      "id": "n107",
      "time": 67000,
      "x": 6,
      "type": "tap"
    },
    {
      "id": "n108",
      "time": 67500,
      "x": 2,
      "type": "tap"
    },
    {
      "id": "n109",
      "time": 67500,
      "x": 6,
      "type": "tap"
    },
    {
      "id": "n110",
      "time": 68000,
      "x": 2,
      "type": "tap"
    },
    {
      "id": "n111",
      "time": 68000,
      "x": 6,
      "type": "tap"
    },
    {
      "id": "n112",
      "time": 68500,
      "x": 2,
      "type": "tap"
    },
    {
      "id": "n113",
      "time": 68500,
      "x": 6,
      "type": "tap"
    },
    {
      "id": "n114",
      "time": 69000,
      "x": 2,
      "type": "tap"
    },
    {
      "id": "n115",
      "time": 69000,
      "x": 6,
      "type": "tap"
    },
    {
      "id": "n116",
      "time": 69750,
      "x": 2,
      "type": "tap"
    },
    {
      "id": "n117",
      "time": 69750,
      "x": 6,
      "type": "tap"
    },
    {
      "id": "n118",
      "time": 70500,
      "x": 2,
      "type": "hold",
      "durationMs": 1500
    },
    {
      "id": "n119",
      "time": 70500,
      "x": 5,
      "type": "hold",
      "durationMs": 1500
    },
    {
      "id": "n120",
      "time": 72000,
      "x": 0,
      "type": "hold",
      "durationMs": 3000
    },
    {
      "id": "n121",
      "time": 72750,
      "x": 3,
      "type": "hold",
      "durationMs": 1130
    },
    {
      "id": "n122",
      "time": 72750,
      "x": 7,
      "type": "hold",
      "durationMs": 1130
    },
    {
      "id": "n123",
      "time": 74000,
      "x": 3,
      "type": "tap"
    },
    {
      "id": "n124",
      "time": 74000,
      "x": 7,
      "type": "tap"
    },
    {
      "id": "n125",
      "time": 74500,
      "x": 3,
      "type": "tap"
    },
    {
      "id": "n126",
      "time": 74500,
      "x": 7,
      "type": "tap"
    },
    {
      "id": "n127",
      "time": 75000,
      "x": 2,
      "type": "tap"
    },
    {
      "id": "n128",
      "time": 75000,
      "x": 6,
      "type": "tap"
    },
    {
      "id": "n129",
      "time": 75500,
      "x": 3,
      "type": "tap"
    },
    {
      "id": "n130",
      "time": 75500,
      "x": 7,
      "type": "tap"
    },
    {
      "id": "n131",
      "time": 76000,
      "x": 2,
      "type": "tap"
    },
    {
      "id": "n132",
      "time": 76000,
      "x": 6,
      "type": "tap"
    },
    {
      "id": "n133",
      "time": 76500,
      "x": 2,
      "type": "tap"
    },
    {
      "id": "n134",
      "time": 76500,
      "x": 6,
      "type": "tap"
    },
    {
      "id": "n135",
      "time": 77000,
      "x": 2,
      "type": "tap"
    },
    {
      "id": "n136",
      "time": 77000,
      "x": 6,
      "type": "tap"
    },
    {
      "id": "n137",
      "time": 77500,
      "x": 2,
      "type": "tap"
    },
    {
      "id": "n138",
      "time": 77500,
      "x": 6,
      "type": "tap"
    },
    {
      "id": "n139",
      "time": 78000,
      "x": 2,
      "type": "tap"
    },
    {
      "id": "n140",
      "time": 78000,
      "x": 7,
      "type": "tap"
    },
    {
      "id": "n141",
      "time": 78581,
      "x": 7,
      "type": "tap"
    },
    {
      "id": "n142",
      "time": 78750,
      "x": 2,
      "type": "tap"
    },
    {
      "id": "n143",
      "time": 79500,
      "x": 2,
      "type": "hold",
      "durationMs": 1500
    },
    {
      "id": "n144",
      "time": 79500,
      "x": 5,
      "type": "hold",
      "durationMs": 2130
    },
    {
      "id": "n145",
      "time": 81000,
      "x": 0,
      "type": "hold",
      "durationMs": 3000
    },
    {
      "id": "n146",
      "time": 81750,
      "x": 1,
      "type": "tap"
    },
    {
      "id": "n147",
      "time": 81750,
      "x": 5,
      "type": "tap"
    },
    {
      "id": "n148",
      "time": 82500,
      "x": 1,
      "type": "tap"
    },
    {
      "id": "n149",
      "time": 82500,
      "x": 5,
      "type": "tap"
    },
    {
      "id": "n150",
      "time": 83250,
      "x": 6,
      "type": "tap"
    },
    {
      "id": "n151",
      "time": 84000,
      "x": 2,
      "type": "tap"
    },
    {
      "id": "n152",
      "time": 84000,
      "x": 5,
      "type": "tap"
    },
    {
      "id": "n153",
      "time": 84750,
      "x": 1,
      "type": "tap"
    },
    {
      "id": "n154",
      "time": 84750,
      "x": 5,
      "type": "tap"
    },
    {
      "id": "n155",
      "time": 85500,
      "x": 0,
      "type": "hold",
      "durationMs": 3000
    },
    {
      "id": "n156",
      "time": 86000,
      "x": 1,
      "type": "tap"
    },
    {
      "id": "n157",
      "time": 86000,
      "x": 5,
      "type": "tap"
    },
    {
      "id": "n158",
      "time": 86500,
      "x": 1,
      "type": "tap"
    },
    {
      "id": "n159",
      "time": 86500,
      "x": 5,
      "type": "tap"
    },
    {
      "id": "n160",
      "time": 87000,
      "x": 1,
      "type": "tap"
    },
    {
      "id": "n161",
      "time": 87000,
      "x": 5,
      "type": "tap"
    },
    {
      "id": "n162",
      "time": 87500,
      "x": 1,
      "type": "tap"
    },
    {
      "id": "n163",
      "time": 87500,
      "x": 5,
      "type": "tap"
    },
    {
      "id": "n164",
      "time": 88000,
      "x": 1,
      "type": "tap"
    },
    {
      "id": "n165",
      "time": 88000,
      "x": 5,
      "type": "tap"
    },
    {
      "id": "n166",
      "time": 88500,
      "x": 1,
      "type": "hold",
      "durationMs": 1500
    },
    {
      "id": "n167",
      "time": 88500,
      "x": 5,
      "type": "hold",
      "durationMs": 1500
    },
    {
      "id": "n168",
      "time": 90000,
      "x": 0,
      "type": "hold",
      "durationMs": 3000
    },
    {
      "id": "n169",
      "time": 90750,
      "x": 1,
      "type": "tap"
    },
    {
      "id": "n170",
      "time": 90750,
      "x": 5,
      "type": "tap"
    },
    {
      "id": "n171",
      "time": 91500,
      "x": 1,
      "type": "tap"
    },
    {
      "id": "n172",
      "time": 91500,
      "x": 5,
      "type": "tap"
    },
    {
      "id": "n173",
      "time": 92250,
      "x": 2,
      "type": "tap"
    },
    {
      "id": "n174",
      "time": 92250,
      "x": 6,
      "type": "tap"
    },
    {
      "id": "n175",
      "time": 93000,
      "x": 2,
      "type": "tap"
    },
    {
      "id": "n176",
      "time": 93000,
      "x": 5,
      "type": "tap"
    },
    {
      "id": "n177",
      "time": 93750,
      "x": 1,
      "type": "tap"
    },
    {
      "id": "n178",
      "time": 93750,
      "x": 5,
      "type": "tap"
    },
    {
      "id": "n179",
      "time": 94500,
      "x": 0,
      "type": "hold",
      "durationMs": 3000
    },
    {
      "id": "n180",
      "time": 95000,
      "x": 1,
      "type": "tap"
    },
    {
      "id": "n181",
      "time": 95000,
      "x": 5,
      "type": "tap"
    },
    {
      "id": "n182",
      "time": 95500,
      "x": 1,
      "type": "tap"
    },
    {
      "id": "n183",
      "time": 95500,
      "x": 5,
      "type": "tap"
    },
    {
      "id": "n184",
      "time": 96000,
      "x": 1,
      "type": "tap"
    },
    {
      "id": "n185",
      "time": 96000,
      "x": 5,
      "type": "tap"
    },
    {
      "id": "n186",
      "time": 96500,
      "x": 1,
      "type": "tap"
    },
    {
      "id": "n187",
      "time": 96500,
      "x": 5,
      "type": "tap"
    },
    {
      "id": "n188",
      "time": 97000,
      "x": 1,
      "type": "tap"
    },
    {
      "id": "n189",
      "time": 97000,
      "x": 5,
      "type": "tap"
    },
    {
      "id": "n190",
      "time": 97500,
      "x": 1,
      "type": "hold",
      "durationMs": 1500
    },
    {
      "id": "n191",
      "time": 97500,
      "x": 5,
      "type": "hold",
      "durationMs": 1500
    },
    {
      "id": "n192",
      "time": 99000,
      "x": 0,
      "type": "hold",
      "durationMs": 3000
    },
    {
      "id": "n193",
      "time": 99750,
      "x": 1,
      "type": "tap"
    },
    {
      "id": "n194",
      "time": 99750,
      "x": 5,
      "type": "tap"
    },
    {
      "id": "n195",
      "time": 100500,
      "x": 1,
      "type": "tap"
    },
    {
      "id": "n196",
      "time": 100500,
      "x": 5,
      "type": "tap"
    },
    {
      "id": "n197",
      "time": 101250,
      "x": 2,
      "type": "tap"
    },
    {
      "id": "n198",
      "time": 101250,
      "x": 6,
      "type": "tap"
    },
    {
      "id": "n199",
      "time": 102000,
      "x": 2,
      "type": "tap"
    },
    {
      "id": "n200",
      "time": 102000,
      "x": 6,
      "type": "tap"
    },
    {
      "id": "n201",
      "time": 102750,
      "x": 2,
      "type": "tap"
    },
    {
      "id": "n202",
      "time": 102750,
      "x": 5,
      "type": "tap"
    },
    {
      "id": "n203",
      "time": 103500,
      "x": 0,
      "type": "hold",
      "durationMs": 3000
    },
    {
      "id": "n204",
      "time": 104000,
      "x": 2,
      "type": "tap"
    },
    {
      "id": "n205",
      "time": 104000,
      "x": 5,
      "type": "tap"
    },
    {
      "id": "n206",
      "time": 104500,
      "x": 2,
      "type": "tap"
    },
    {
      "id": "n207",
      "time": 104500,
      "x": 5,
      "type": "tap"
    },
    {
      "id": "n208",
      "time": 105000,
      "x": 2,
      "type": "tap"
    },
    {
      "id": "n209",
      "time": 105000,
      "x": 5,
      "type": "tap"
    },
    {
      "id": "n210",
      "time": 105500,
      "x": 2,
      "type": "tap"
    },
    {
      "id": "n211",
      "time": 105500,
      "x": 5,
      "type": "tap"
    },
    {
      "id": "n212",
      "time": 106000,
      "x": 2,
      "type": "tap"
    },
    {
      "id": "n213",
      "time": 106000,
      "x": 6,
      "type": "tap"
    },
    {
      "id": "n214",
      "time": 106500,
      "x": 2,
      "type": "tap"
    },
    {
      "id": "n215",
      "time": 106500,
      "x": 5,
      "type": "tap"
    },
    {
      "id": "n216",
      "time": 107000,
      "x": 2,
      "type": "tap"
    },
    {
      "id": "n217",
      "time": 107000,
      "x": 6,
      "type": "tap"
    },
    {
      "id": "n218",
      "time": 107500,
      "x": 2,
      "type": "tap"
    },
    {
      "id": "n219",
      "time": 107500,
      "x": 6,
      "type": "tap"
    },
    {
      "id": "n220",
      "time": 108000,
      "x": 3,
      "type": "hold",
      "durationMs": 3000
    },
    {
      "id": "n221",
      "time": 108000,
      "x": 7,
      "type": "hold",
      "durationMs": 2880
    },
    {
      "id": "n222",
      "time": 111000,
      "x": 2,
      "type": "hold",
      "durationMs": 1380
    },
    {
      "id": "n223",
      "time": 111000,
      "x": 7,
      "type": "hold",
      "durationMs": 1380
    },
    {
      "id": "n224",
      "time": 112500,
      "x": 2,
      "type": "hold",
      "durationMs": 3000
    },
    {
      "id": "n225",
      "time": 112500,
      "x": 7,
      "type": "hold",
      "durationMs": 3000
    },
    {
      "id": "n226",
      "time": 115500,
      "x": 1,
      "type": "hold",
      "durationMs": 1500
    },
    {
      "id": "n227",
      "time": 115500,
      "x": 5,
      "type": "hold",
      "durationMs": 1500
    },
    {
      "id": "n228",
      "time": 117000,
      "x": 0,
      "type": "tap"
    },
    {
      "id": "n229",
      "time": 117000,
      "x": 4,
      "type": "tap"
    },
    {
      "id": "n230",
      "time": 117500,
      "x": 0,
      "type": "tap"
    },
    {
      "id": "n231",
      "time": 118000,
      "x": 4,
      "type": "tap"
    },
    {
      "id": "n232",
      "time": 118500,
      "x": 0,
      "type": "hold",
      "durationMs": 1380
    },
    {
      "id": "n233",
      "time": 119000,
      "x": 1,
      "type": "tap"
    },
    {
      "id": "n234",
      "time": 119250,
      "x": 4,
      "type": "tap"
    },
    {
      "id": "n235",
      "time": 120000,
      "x": 0,
      "type": "hold",
      "durationMs": 1380
    },
    {
      "id": "n236",
      "time": 120000,
      "x": 5,
      "type": "hold",
      "durationMs": 1000
    },
    {
      "id": "n237",
      "time": 120500,
      "x": 1,
      "type": "tap"
    },
    {
      "id": "n238",
      "time": 120750,
      "x": 4,
      "type": "tap"
    },
    {
      "id": "n239",
      "time": 121250,
      "x": 5,
      "type": "tap"
    },
    {
      "id": "n240",
      "time": 121500,
      "x": 0,
      "type": "tap"
    },
    {
      "id": "n241",
      "time": 122000,
      "x": 0,
      "type": "tap"
    },
    {
      "id": "n242",
      "time": 122500,
      "x": 4,
      "type": "tap"
    },
    {
      "id": "n243",
      "time": 123000,
      "x": 0,
      "type": "hold",
      "durationMs": 1380
    },
    {
      "id": "n244",
      "time": 123500,
      "x": 1,
      "type": "tap"
    },
    {
      "id": "n245",
      "time": 123750,
      "x": 4,
      "type": "tap"
    },
    {
      "id": "n246",
      "time": 124500,
      "x": 0,
      "type": "hold",
      "durationMs": 1380
    },
    {
      "id": "n247",
      "time": 124500,
      "x": 5,
      "type": "hold",
      "durationMs": 1000
    },
    {
      "id": "n248",
      "time": 125000,
      "x": 1,
      "type": "tap"
    },
    {
      "id": "n249",
      "time": 125250,
      "x": 4,
      "type": "tap"
    },
    {
      "id": "n250",
      "time": 125750,
      "x": 4,
      "type": "tap"
    },
    {
      "id": "n251",
      "time": 126000,
      "x": 0,
      "type": "tap"
    },
    {
      "id": "n252",
      "time": 126500,
      "x": 0,
      "type": "tap"
    },
    {
      "id": "n253",
      "time": 127000,
      "x": 1,
      "type": "tap"
    },
    {
      "id": "n254",
      "time": 127000,
      "x": 5,
      "type": "tap"
    },
    {
      "id": "n255",
      "time": 127500,
      "x": 3,
      "type": "tap"
    },
    {
      "id": "n256",
      "time": 127500,
      "x": 6,
      "type": "hold",
      "durationMs": 1500
    },
    {
      "id": "n257",
      "time": 128000,
      "x": 3,
      "type": "tap"
    },
    {
      "id": "n258",
      "time": 128500,
      "x": 1,
      "type": "tap"
    },
    {
      "id": "n259",
      "time": 129000,
      "x": 1,
      "type": "tap"
    },
    {
      "id": "n260",
      "time": 129000,
      "x": 4,
      "type": "hold",
      "durationMs": 1000
    },
    {
      "id": "n261",
      "time": 129500,
      "x": 0,
      "type": "tap"
    },
    {
      "id": "n262",
      "time": 130000,
      "x": 0,
      "type": "tap"
    },
    {
      "id": "n263",
      "time": 130000,
      "x": 6,
      "type": "tap"
    },
    {
      "id": "n264",
      "time": 130500,
      "x": 0,
      "type": "tap"
    },
    {
      "id": "n265",
      "time": 130500,
      "x": 6,
      "type": "tap"
    },
    {
      "id": "n266",
      "time": 131000,
      "x": 1,
      "type": "tap"
    },
    {
      "id": "n267",
      "time": 131000,
      "x": 6,
      "type": "tap"
    },
    {
      "id": "n268",
      "time": 131500,
      "x": 2,
      "type": "tap"
    },
    {
      "id": "n269",
      "time": 131500,
      "x": 5,
      "type": "tap"
    },
    {
      "id": "n270",
      "time": 132000,
      "x": 3,
      "type": "tap"
    },
    {
      "id": "n271",
      "time": 132000,
      "x": 5,
      "type": "hold",
      "durationMs": 1500
    },
    {
      "id": "n272",
      "time": 132500,
      "x": 2,
      "type": "tap"
    },
    {
      "id": "n273",
      "time": 132500,
      "x": 4,
      "type": "tap"
    },
    {
      "id": "n274",
      "time": 133000,
      "x": 1,
      "type": "tap"
    },
    {
      "id": "n275",
      "time": 133000,
      "x": 4,
      "type": "tap"
    },
    {
      "id": "n276",
      "time": 133500,
      "x": 0,
      "type": "tap"
    },
    {
      "id": "n277",
      "time": 133500,
      "x": 4,
      "type": "tap"
    },
    {
      "id": "n278",
      "time": 134000,
      "x": 1,
      "type": "tap"
    },
    {
      "id": "n279",
      "time": 134250,
      "x": 4,
      "type": "tap"
    },
    {
      "id": "n280",
      "time": 134500,
      "x": 1,
      "type": "tap"
    },
    {
      "id": "n281",
      "time": 135000,
      "x": 0,
      "type": "hold",
      "durationMs": 1380
    },
    {
      "id": "n282",
      "time": 135000,
      "x": 5,
      "type": "hold",
      "durationMs": 3000
    },
    {
      "id": "n283",
      "time": 135500,
      "x": 1,
      "type": "tap"
    },
    {
      "id": "n284",
      "time": 136000,
      "x": 4,
      "type": "tap"
    },
    {
      "id": "n285",
      "time": 136500,
      "x": 0,
      "type": "hold",
      "durationMs": 1380
    },
    {
      "id": "n286",
      "time": 137000,
      "x": 1,
      "type": "tap"
    },
    {
      "id": "n287",
      "time": 137500,
      "x": 4,
      "type": "tap"
    },
    {
      "id": "n288",
      "time": 138000,
      "x": 0,
      "type": "hold",
      "durationMs": 1380
    },
    {
      "id": "n289",
      "time": 138000,
      "x": 6,
      "type": "hold",
      "durationMs": 1000
    },
    {
      "id": "n290",
      "time": 138500,
      "x": 1,
      "type": "tap"
    },
    {
      "id": "n291",
      "time": 139000,
      "x": 2,
      "type": "tap"
    },
    {
      "id": "n292",
      "time": 139000,
      "x": 5,
      "type": "tap"
    },
    {
      "id": "n293",
      "time": 139500,
      "x": 0,
      "type": "hold",
      "durationMs": 1380
    },
    {
      "id": "n294",
      "time": 139500,
      "x": 5,
      "type": "hold",
      "durationMs": 3000
    },
    {
      "id": "n295",
      "time": 140000,
      "x": 1,
      "type": "tap"
    },
    {
      "id": "n296",
      "time": 140500,
      "x": 4,
      "type": "tap"
    },
    {
      "id": "n297",
      "time": 141000,
      "x": 0,
      "type": "hold",
      "durationMs": 1380
    },
    {
      "id": "n298",
      "time": 141500,
      "x": 1,
      "type": "tap"
    },
    {
      "id": "n299",
      "time": 142000,
      "x": 4,
      "type": "tap"
    },
    {
      "id": "n300",
      "time": 142500,
      "x": 0,
      "type": "hold",
      "durationMs": 1380
    },
    {
      "id": "n301",
      "time": 142500,
      "x": 6,
      "type": "hold",
      "durationMs": 1000
    },
    {
      "id": "n302",
      "time": 143000,
      "x": 1,
      "type": "tap"
    },
    {
      "id": "n303",
      "time": 143500,
      "x": 2,
      "type": "tap"
    },
    {
      "id": "n304",
      "time": 143500,
      "x": 5,
      "type": "tap"
    },
    {
      "id": "n305",
      "time": 144000,
      "x": 0,
      "type": "hold",
      "durationMs": 1500
    },
    {
      "id": "n306",
      "time": 144000,
      "x": 7,
      "type": "hold",
      "durationMs": 2130
    },
    {
      "id": "n307",
      "time": 144500,
      "x": 1,
      "type": "tap"
    },
    {
      "id": "n308",
      "time": 145000,
      "x": 2,
      "type": "tap"
    },
    {
      "id": "n309",
      "time": 145500,
      "x": 3,
      "type": "tap"
    },
    {
      "id": "n310",
      "time": 145750,
      "x": 5,
      "type": "tap"
    },
    {
      "id": "n311",
      "time": 146250,
      "x": 3,
      "type": "tap"
    },
    {
      "id": "n312",
      "time": 146250,
      "x": 7,
      "type": "tap"
    },
    {
      "id": "n313",
      "time": 146750,
      "x": 5,
      "type": "tap"
    },
    {
      "id": "n314",
      "time": 147000,
      "x": 2,
      "type": "tap"
    },
    {
      "id": "n315",
      "time": 147250,
      "x": 5,
      "type": "tap"
    },
    {
      "id": "n316",
      "time": 147750,
      "x": 2,
      "type": "tap"
    },
    {
      "id": "n317",
      "time": 147750,
      "x": 6,
      "type": "tap"
    },
    {
      "id": "n318",
      "time": 148250,
      "x": 5,
      "type": "tap"
    },
    {
      "id": "n319",
      "time": 148500,
      "x": 2,
      "type": "hold",
      "durationMs": 1380
    },
    {
      "id": "n320",
      "time": 149000,
      "x": 3,
      "type": "tap"
    },
    {
      "id": "n321",
      "time": 149250,
      "x": 5,
      "type": "tap"
    },
    {
      "id": "n322",
      "time": 150000,
      "x": 2,
      "type": "hold",
      "durationMs": 1500
    },
    {
      "id": "n323",
      "time": 150500,
      "x": 3,
      "type": "tap"
    },
    {
      "id": "n324",
      "time": 150750,
      "x": 5,
      "type": "tap"
    },
    {
      "id": "n325",
      "time": 151500,
      "x": 1,
      "type": "hold",
      "durationMs": 1500
    },
    {
      "id": "n326",
      "time": 151500,
      "x": 7,
      "type": "hold",
      "durationMs": 1380
    },
    {
      "id": "n327",
      "time": 152000,
      "x": 3,
      "type": "tap"
    },
    {
      "id": "n328",
      "time": 152250,
      "x": 6,
      "type": "tap"
    },
    {
      "id": "n329",
      "time": 153000,
      "x": 0,
      "type": "hold",
      "durationMs": 1500
    },
    {
      "id": "n330",
      "time": 153000,
      "x": 7,
      "type": "hold",
      "durationMs": 2880
    },
    {
      "id": "n331",
      "time": 153500,
      "x": 2,
      "type": "tap"
    },
    {
      "id": "n332",
      "time": 154000,
      "x": 5,
      "type": "tap"
    },
    {
      "id": "n333",
      "time": 154500,
      "x": 1,
      "type": "hold",
      "durationMs": 1380
    },
    {
      "id": "n334",
      "time": 155000,
      "x": 3,
      "type": "tap"
    },
    {
      "id": "n335",
      "time": 155500,
      "x": 6,
      "type": "tap"
    },
    {
      "id": "n336",
      "time": 156000,
      "x": 1,
      "type": "hold",
      "durationMs": 1500
    },
    {
      "id": "n337",
      "time": 156000,
      "x": 7,
      "type": "hold",
      "durationMs": 1000
    },
    {
      "id": "n338",
      "time": 156500,
      "x": 3,
      "type": "tap"
    },
    {
      "id": "n339",
      "time": 156750,
      "x": 6,
      "type": "tap"
    },
    {
      "id": "n340",
      "time": 157250,
      "x": 7,
      "type": "tap"
    },
    {
      "id": "n341",
      "time": 157500,
      "x": 0,
      "type": "hold",
      "durationMs": 1500
    },
    {
      "id": "n342",
      "time": 158000,
      "x": 2,
      "type": "tap"
    },
    {
      "id": "n343",
      "time": 158500,
      "x": 5,
      "type": "tap"
    },
    {
      "id": "n344",
      "time": 159000,
      "x": 1,
      "type": "hold",
      "durationMs": 1380
    },
    {
      "id": "n345",
      "time": 159500,
      "x": 3,
      "type": "tap"
    },
    {
      "id": "n346",
      "time": 160000,
      "x": 6,
      "type": "tap"
    },
    {
      "id": "n347",
      "time": 160500,
      "x": 1,
      "type": "hold",
      "durationMs": 1500
    },
    {
      "id": "n348",
      "time": 160500,
      "x": 7,
      "type": "hold",
      "durationMs": 1000
    },
    {
      "id": "n349",
      "time": 161000,
      "x": 3,
      "type": "tap"
    },
    {
      "id": "n350",
      "time": 161250,
      "x": 6,
      "type": "tap"
    },
    {
      "id": "n351",
      "time": 161750,
      "x": 6,
      "type": "tap"
    },
    {
      "id": "n352",
      "time": 162000,
      "x": 2,
      "type": "hold",
      "durationMs": 1380
    },
    {
      "id": "n353",
      "time": 162500,
      "x": 3,
      "type": "tap"
    },
    {
      "id": "n354",
      "time": 162750,
      "x": 6,
      "type": "tap"
    },
    {
      "id": "n355",
      "time": 163250,
      "x": 6,
      "type": "tap"
    },
    {
      "id": "n356",
      "time": 163500,
      "x": 2,
      "type": "hold",
      "durationMs": 1380
    },
    {
      "id": "n357",
      "time": 164000,
      "x": 3,
      "type": "tap"
    },
    {
      "id": "n358",
      "time": 164250,
      "x": 6,
      "type": "tap"
    },
    {
      "id": "n359",
      "time": 164750,
      "x": 7,
      "type": "tap"
    },
    {
      "id": "n360",
      "time": 165000,
      "x": 2,
      "type": "hold",
      "durationMs": 1500
    },
    {
      "id": "n361",
      "time": 165500,
      "x": 3,
      "type": "tap"
    },
    {
      "id": "n362",
      "time": 165750,
      "x": 7,
      "type": "tap"
    },
    {
      "id": "n363",
      "time": 166250,
      "x": 7,
      "type": "tap"
    },
    {
      "id": "n364",
      "time": 166500,
      "x": 3,
      "type": "tap"
    },
    {
      "id": "n365",
      "time": 167000,
      "x": 3,
      "type": "tap"
    },
    {
      "id": "n366",
      "time": 167250,
      "x": 7,
      "type": "tap"
    },
    {
      "id": "n367",
      "time": 167750,
      "x": 7,
      "type": "tap"
    },
    {
      "id": "n368",
      "time": 168000,
      "x": 3,
      "type": "tap"
    },
    {
      "id": "n369",
      "time": 168500,
      "x": 3,
      "type": "tap"
    },
    {
      "id": "n370",
      "time": 168750,
      "x": 7,
      "type": "tap"
    },
    {
      "id": "n371",
      "time": 169250,
      "x": 7,
      "type": "tap"
    },
    {
      "id": "n372",
      "time": 169500,
      "x": 3,
      "type": "tap"
    },
    {
      "id": "n373",
      "time": 170000,
      "x": 3,
      "type": "tap"
    },
    {
      "id": "n374",
      "time": 170250,
      "x": 7,
      "type": "tap"
    },
    {
      "id": "n375",
      "time": 170750,
      "x": 7,
      "type": "tap"
    },
    {
      "id": "n376",
      "time": 171000,
      "x": 2,
      "type": "hold",
      "durationMs": 1380
    },
    {
      "id": "n377",
      "time": 171500,
      "x": 3,
      "type": "tap"
    },
    {
      "id": "n378",
      "time": 171750,
      "x": 7,
      "type": "tap"
    },
    {
      "id": "n379",
      "time": 172250,
      "x": 7,
      "type": "tap"
    },
    {
      "id": "n380",
      "time": 172500,
      "x": 2,
      "type": "hold",
      "durationMs": 1380
    },
    {
      "id": "n381",
      "time": 173000,
      "x": 3,
      "type": "tap"
    },
    {
      "id": "n382",
      "time": 173250,
      "x": 7,
      "type": "tap"
    },
    {
      "id": "n383",
      "time": 173750,
      "x": 7,
      "type": "tap"
    },
    {
      "id": "n384",
      "time": 174000,
      "x": 2,
      "type": "hold",
      "durationMs": 1380
    },
    {
      "id": "n385",
      "time": 174500,
      "x": 3,
      "type": "tap"
    },
    {
      "id": "n386",
      "time": 175000,
      "x": 7,
      "type": "tap"
    },
    {
      "id": "n387",
      "time": 175500,
      "x": 2,
      "type": "hold",
      "durationMs": 1380
    },
    {
      "id": "n388",
      "time": 175500,
      "x": 7,
      "type": "hold",
      "durationMs": 3000
    },
    {
      "id": "n389",
      "time": 176000,
      "x": 3,
      "type": "tap"
    },
    {
      "id": "n390",
      "time": 176250,
      "x": 5,
      "type": "tap"
    },
    {
      "id": "n391",
      "time": 176750,
      "x": 5,
      "type": "tap"
    },
    {
      "id": "n392",
      "time": 177000,
      "x": 2,
      "type": "tap"
    },
    {
      "id": "n393",
      "time": 177500,
      "x": 2,
      "type": "tap"
    },
    {
      "id": "n394",
      "time": 177750,
      "x": 5,
      "type": "tap"
    },
    {
      "id": "n395",
      "time": 178250,
      "x": 5,
      "type": "tap"
    },
    {
      "id": "n396",
      "time": 178500,
      "x": 1,
      "type": "hold",
      "durationMs": 1380
    },
    {
      "id": "n397",
      "time": 179000,
      "x": 2,
      "type": "tap"
    },
    {
      "id": "n398",
      "time": 179500,
      "x": 6,
      "type": "tap"
    },
    {
      "id": "n399",
      "time": 180000,
      "x": 1,
      "type": "hold",
      "durationMs": 4500
    },
    {
      "id": "n400",
      "time": 180000,
      "x": 7,
      "type": "tap"
    },
    {
      "id": "n401",
      "time": 180500,
      "x": 2,
      "type": "tap"
    },
    {
      "id": "n402",
      "time": 180500,
      "x": 7,
      "type": "tap"
    },
    {
      "id": "n403",
      "time": 181000,
      "x": 3,
      "type": "tap"
    },
    {
      "id": "n404",
      "time": 181000,
      "x": 7,
      "type": "tap"
    },
    {
      "id": "n405",
      "time": 181500,
      "x": 3,
      "type": "tap"
    },
    {
      "id": "n406",
      "time": 181500,
      "x": 7,
      "type": "tap"
    },
    {
      "id": "n407",
      "time": 182000,
      "x": 3,
      "type": "tap"
    },
    {
      "id": "n408",
      "time": 182250,
      "x": 7,
      "type": "hold",
      "durationMs": 1250
    },
    {
      "id": "n409",
      "time": 182500,
      "x": 3,
      "type": "tap"
    },
    {
      "id": "n410",
      "time": 183000,
      "x": 2,
      "type": "tap"
    },
    {
      "id": "n411",
      "time": 183500,
      "x": 2,
      "type": "tap"
    },
    {
      "id": "n412",
      "time": 183500,
      "x": 6,
      "type": "tap"
    },
    {
      "id": "n413",
      "time": 184000,
      "x": 2,
      "type": "tap"
    },
    {
      "id": "n414",
      "time": 184000,
      "x": 6,
      "type": "tap"
    },
    {
      "id": "n415",
      "time": 184500,
      "x": 0,
      "type": "tap"
    },
    {
      "id": "n416",
      "time": 184500,
      "x": 6,
      "type": "tap"
    },
    {
      "id": "n417",
      "time": 185000,
      "x": 1,
      "type": "tap"
    },
    {
      "id": "n418",
      "time": 185000,
      "x": 6,
      "type": "tap"
    },
    {
      "id": "n419",
      "time": 185500,
      "x": 2,
      "type": "tap"
    },
    {
      "id": "n420",
      "time": 185500,
      "x": 5,
      "type": "tap"
    },
    {
      "id": "n421",
      "time": 186000,
      "x": 2,
      "type": "tap"
    },
    {
      "id": "n422",
      "time": 186000,
      "x": 5,
      "type": "tap"
    },
    {
      "id": "n423",
      "time": 186500,
      "x": 2,
      "type": "tap"
    },
    {
      "id": "n424",
      "time": 186500,
      "x": 5,
      "type": "tap"
    },
    {
      "id": "n425",
      "time": 187000,
      "x": 1,
      "type": "tap"
    },
    {
      "id": "n426",
      "time": 187000,
      "x": 4,
      "type": "tap"
    },
    {
      "id": "n427",
      "time": 187500,
      "x": 0,
      "type": "tap"
    },
    {
      "id": "n428",
      "time": 187500,
      "x": 4,
      "type": "tap"
    },
    {
      "id": "n429",
      "time": 188000,
      "x": 0,
      "type": "tap"
    },
    {
      "id": "n430",
      "time": 188000,
      "x": 4,
      "type": "tap"
    },
    {
      "id": "n431",
      "time": 188500,
      "x": 0,
      "type": "tap"
    },
    {
      "id": "n432",
      "time": 188500,
      "x": 4,
      "type": "tap"
    },
    {
      "id": "n433",
      "time": 189000,
      "x": 0,
      "type": "tap"
    },
    {
      "id": "n434",
      "time": 189000,
      "x": 4,
      "type": "tap"
    },
    {
      "id": "n435",
      "time": 189500,
      "x": 0,
      "type": "tap"
    },
    {
      "id": "n436",
      "time": 190000,
      "x": 0,
      "type": "tap"
    },
    {
      "id": "n437",
      "time": 190000,
      "x": 4,
      "type": "tap"
    },
    {
      "id": "n438",
      "time": 190500,
      "x": 0,
      "type": "tap"
    },
    {
      "id": "n439",
      "time": 190500,
      "x": 4,
      "type": "hold",
      "durationMs": 1000
    },
    {
      "id": "n440",
      "time": 191000,
      "x": 0,
      "type": "tap"
    },
    {
      "id": "n441",
      "time": 191500,
      "x": 0,
      "type": "tap"
    },
    {
      "id": "n442",
      "time": 192000,
      "x": 0,
      "type": "tap"
    },
    {
      "id": "n443",
      "time": 192000,
      "x": 4,
      "type": "tap"
    },
    {
      "id": "n444",
      "time": 192500,
      "x": 0,
      "type": "tap"
    },
    {
      "id": "n445",
      "time": 193000,
      "x": 0,
      "type": "tap"
    },
    {
      "id": "n446",
      "time": 193000,
      "x": 4,
      "type": "tap"
    },
    {
      "id": "n447",
      "time": 193500,
      "x": 0,
      "type": "tap"
    },
    {
      "id": "n448",
      "time": 193500,
      "x": 4,
      "type": "tap"
    },
    {
      "id": "n449",
      "time": 194000,
      "x": 0,
      "type": "tap"
    },
    {
      "id": "n450",
      "time": 194500,
      "x": 0,
      "type": "tap"
    },
    {
      "id": "n451",
      "time": 194500,
      "x": 4,
      "type": "tap"
    },
    {
      "id": "n452",
      "time": 195000,
      "x": 0,
      "type": "tap"
    },
    {
      "id": "n453",
      "time": 195000,
      "x": 4,
      "type": "hold",
      "durationMs": 1000
    },
    {
      "id": "n454",
      "time": 195500,
      "x": 0,
      "type": "tap"
    },
    {
      "id": "n455",
      "time": 196000,
      "x": 0,
      "type": "tap"
    },
    {
      "id": "n456",
      "time": 196500,
      "x": 0,
      "type": "tap"
    },
    {
      "id": "n457",
      "time": 196500,
      "x": 4,
      "type": "tap"
    },
    {
      "id": "n458",
      "time": 197000,
      "x": 0,
      "type": "tap"
    },
    {
      "id": "n459",
      "time": 197500,
      "x": 0,
      "type": "tap"
    },
    {
      "id": "n460",
      "time": 197500,
      "x": 4,
      "type": "tap"
    },
    {
      "id": "n461",
      "time": 198000,
      "x": 0,
      "type": "tap"
    },
    {
      "id": "n462",
      "time": 198000,
      "x": 4,
      "type": "tap"
    },
    {
      "id": "n463",
      "time": 198500,
      "x": 0,
      "type": "tap"
    },
    {
      "id": "n464",
      "time": 198500,
      "x": 5,
      "type": "tap"
    },
    {
      "id": "n465",
      "time": 199000,
      "x": 0,
      "type": "tap"
    },
    {
      "id": "n466",
      "time": 199000,
      "x": 5,
      "type": "tap"
    },
    {
      "id": "n467",
      "time": 199500,
      "x": 1,
      "type": "tap"
    },
    {
      "id": "n468",
      "time": 199500,
      "x": 4,
      "type": "tap"
    },
    {
      "id": "n469",
      "time": 200000,
      "x": 1,
      "type": "tap"
    },
    {
      "id": "n470",
      "time": 200000,
      "x": 4,
      "type": "tap"
    },
    {
      "id": "n471",
      "time": 200500,
      "x": 1,
      "type": "tap"
    },
    {
      "id": "n472",
      "time": 200500,
      "x": 4,
      "type": "tap"
    },
    {
      "id": "n473",
      "time": 201000,
      "x": 1,
      "type": "tap"
    },
    {
      "id": "n474",
      "time": 201000,
      "x": 4,
      "type": "tap"
    },
    {
      "id": "n475",
      "time": 201500,
      "x": 0,
      "type": "tap"
    },
    {
      "id": "n476",
      "time": 201500,
      "x": 4,
      "type": "tap"
    },
    {
      "id": "n477",
      "time": 202000,
      "x": 0,
      "type": "tap"
    },
    {
      "id": "n478",
      "time": 202000,
      "x": 4,
      "type": "tap"
    },
    {
      "id": "n479",
      "time": 202500,
      "x": 0,
      "type": "tap"
    },
    {
      "id": "n480",
      "time": 202500,
      "x": 4,
      "type": "tap"
    },
    {
      "id": "n481",
      "time": 203000,
      "x": 0,
      "type": "tap"
    },
    {
      "id": "n482",
      "time": 203000,
      "x": 5,
      "type": "tap"
    },
    {
      "id": "n483",
      "time": 203500,
      "x": 0,
      "type": "tap"
    },
    {
      "id": "n484",
      "time": 203500,
      "x": 5,
      "type": "tap"
    },
    {
      "id": "n485",
      "time": 204000,
      "x": 1,
      "type": "tap"
    },
    {
      "id": "n486",
      "time": 204000,
      "x": 4,
      "type": "tap"
    },
    {
      "id": "n487",
      "time": 204500,
      "x": 1,
      "type": "tap"
    },
    {
      "id": "n488",
      "time": 204500,
      "x": 4,
      "type": "tap"
    },
    {
      "id": "n489",
      "time": 205000,
      "x": 1,
      "type": "tap"
    },
    {
      "id": "n490",
      "time": 205000,
      "x": 4,
      "type": "tap"
    },
    {
      "id": "n491",
      "time": 205500,
      "x": 1,
      "type": "tap"
    },
    {
      "id": "n492",
      "time": 205500,
      "x": 4,
      "type": "tap"
    },
    {
      "id": "n493",
      "time": 206000,
      "x": 1,
      "type": "tap"
    },
    {
      "id": "n494",
      "time": 206000,
      "x": 4,
      "type": "tap"
    },
    {
      "id": "n495",
      "time": 206500,
      "x": 1,
      "type": "tap"
    },
    {
      "id": "n496",
      "time": 206500,
      "x": 4,
      "type": "tap"
    },
    {
      "id": "n497",
      "time": 207000,
      "x": 1,
      "type": "tap"
    },
    {
      "id": "n498",
      "time": 207000,
      "x": 6,
      "type": "hold",
      "durationMs": 3000
    },
    {
      "id": "n499",
      "time": 207500,
      "x": 5,
      "type": "tap"
    },
    {
      "id": "n500",
      "time": 208000,
      "x": 1,
      "type": "tap"
    },
    {
      "id": "n501",
      "time": 208000,
      "x": 5,
      "type": "tap"
    },
    {
      "id": "n502",
      "time": 208500,
      "x": 2,
      "type": "hold",
      "durationMs": 1000
    },
    {
      "id": "n503",
      "time": 208750,
      "x": 4,
      "type": "tap"
    },
    {
      "id": "n504",
      "time": 209250,
      "x": 5,
      "type": "tap"
    },
    {
      "id": "n505",
      "time": 209750,
      "x": 4,
      "type": "tap"
    },
    {
      "id": "n506",
      "time": 210000,
      "x": 2,
      "type": "hold",
      "durationMs": 1500
    },
    {
      "id": "n507",
      "time": 210500,
      "x": 3,
      "type": "tap"
    },
    {
      "id": "n508",
      "time": 211000,
      "x": 6,
      "type": "tap"
    },
    {
      "id": "n509",
      "time": 211500,
      "x": 1,
      "type": "tap"
    },
    {
      "id": "n510",
      "time": 211500,
      "x": 6,
      "type": "hold",
      "durationMs": 3000
    },
    {
      "id": "n511",
      "time": 212000,
      "x": 5,
      "type": "tap"
    },
    {
      "id": "n512",
      "time": 212500,
      "x": 1,
      "type": "tap"
    },
    {
      "id": "n513",
      "time": 212500,
      "x": 5,
      "type": "tap"
    },
    {
      "id": "n514",
      "time": 213000,
      "x": 2,
      "type": "hold",
      "durationMs": 1000
    },
    {
      "id": "n515",
      "time": 213250,
      "x": 4,
      "type": "tap"
    },
    {
      "id": "n516",
      "time": 213750,
      "x": 5,
      "type": "tap"
    },
    {
      "id": "n517",
      "time": 214250,
      "x": 4,
      "type": "tap"
    },
    {
      "id": "n518",
      "time": 214500,
      "x": 2,
      "type": "hold",
      "durationMs": 1500
    },
    {
      "id": "n519",
      "time": 215000,
      "x": 3,
      "type": "tap"
    },
    {
      "id": "n520",
      "time": 215500,
      "x": 6,
      "type": "tap"
    },
    {
      "id": "n521",
      "time": 216000,
      "x": 3,
      "type": "tap"
    },
    {
      "id": "n522",
      "time": 216000,
      "x": 7,
      "type": "hold",
      "durationMs": 1130
    },
    {
      "id": "n523",
      "time": 216500,
      "x": 3,
      "type": "tap"
    },
    {
      "id": "n524",
      "time": 216750,
      "x": 6,
      "type": "tap"
    },
    {
      "id": "n525",
      "time": 217250,
      "x": 7,
      "type": "tap"
    },
    {
      "id": "n526",
      "time": 217750,
      "x": 3,
      "type": "tap"
    },
    {
      "id": "n527",
      "time": 218250,
      "x": 6,
      "type": "tap"
    },
    {
      "id": "n528",
      "time": 218750,
      "x": 7,
      "type": "tap"
    },
    {
      "id": "n529",
      "time": 219250,
      "x": 3,
      "type": "tap"
    },
    {
      "id": "n530",
      "time": 219750,
      "x": 6,
      "type": "tap"
    },
    {
      "id": "n531",
      "time": 220250,
      "x": 7,
      "type": "tap"
    },
    {
      "id": "n532",
      "time": 220500,
      "x": 3,
      "type": "tap"
    },
    {
      "id": "n533",
      "time": 221000,
      "x": 3,
      "type": "tap"
    },
    {
      "id": "n534",
      "time": 221250,
      "x": 6,
      "type": "tap"
    },
    {
      "id": "n535",
      "time": 221750,
      "x": 7,
      "type": "tap"
    },
    {
      "id": "n536",
      "time": 222250,
      "x": 3,
      "type": "tap"
    },
    {
      "id": "n537",
      "time": 222750,
      "x": 6,
      "type": "tap"
    },
    {
      "id": "n538",
      "time": 223250,
      "x": 7,
      "type": "tap"
    },
    {
      "id": "n539",
      "time": 223750,
      "x": 3,
      "type": "tap"
    },
    {
      "id": "n540",
      "time": 224250,
      "x": 6,
      "type": "tap"
    },
    {
      "id": "n541",
      "time": 224750,
      "x": 7,
      "type": "tap"
    },
    {
      "id": "n542",
      "time": 225000,
      "x": 3,
      "type": "tap"
    },
    {
      "id": "n543",
      "time": 225500,
      "x": 3,
      "type": "tap"
    },
    {
      "id": "n544",
      "time": 226000,
      "x": 3,
      "type": "tap"
    },
    {
      "id": "n545",
      "time": 226500,
      "x": 7,
      "type": "hold",
      "durationMs": 1380
    },
    {
      "id": "n546",
      "time": 228000,
      "x": 3,
      "type": "hold",
      "durationMs": 1380
    },
    {
      "id": "n547",
      "time": 228000,
      "x": 7,
      "type": "hold",
      "durationMs": 1880
    },
    {
      "id": "n548",
      "time": 229500,
      "x": 3,
      "type": "tap"
    },
    {
      "id": "n549",
      "time": 230000,
      "x": 3,
      "type": "tap"
    },
    {
      "id": "n550",
      "time": 230000,
      "x": 7,
      "type": "tap"
    },
    {
      "id": "n551",
      "time": 230500,
      "x": 3,
      "type": "tap"
    },
    {
      "id": "n552",
      "time": 230500,
      "x": 7,
      "type": "tap"
    },
    {
      "id": "n553",
      "time": 231000,
      "x": 7,
      "type": "hold",
      "durationMs": 3380
    },
    {
      "id": "n554",
      "time": 232500,
      "x": 3,
      "type": "hold",
      "durationMs": 1380
    },
    {
      "id": "n555",
      "time": 234000,
      "x": 3,
      "type": "tap"
    },
    {
      "id": "n556",
      "time": 234500,
      "x": 3,
      "type": "tap"
    },
    {
      "id": "n557",
      "time": 234500,
      "x": 7,
      "type": "tap"
    },
    {
      "id": "n558",
      "time": 235000,
      "x": 3,
      "type": "tap"
    },
    {
      "id": "n559",
      "time": 235000,
      "x": 7,
      "type": "tap"
    },
    {
      "id": "n560",
      "time": 235500,
      "x": 7,
      "type": "tap"
    },
    {
      "id": "n561",
      "time": 236250,
      "x": 7,
      "type": "hold",
      "durationMs": 1380
    },
    {
      "id": "n562",
      "time": 237000,
      "x": 3,
      "type": "hold",
      "durationMs": 1500
    },
    {
      "id": "n563",
      "time": 237750,
      "x": 7,
      "type": "hold",
      "durationMs": 1130
    },
    {
      "id": "n564",
      "time": 238500,
      "x": 2,
      "type": "hold",
      "durationMs": 2880
    },
    {
      "id": "n565",
      "time": 239000,
      "x": 3,
      "type": "tap"
    },
    {
      "id": "n566",
      "time": 239000,
      "x": 7,
      "type": "tap"
    },
    {
      "id": "n567",
      "time": 239500,
      "x": 3,
      "type": "tap"
    },
    {
      "id": "n568",
      "time": 239500,
      "x": 7,
      "type": "tap"
    },
    {
      "id": "n569",
      "time": 240000,
      "x": 7,
      "type": "hold",
      "durationMs": 3000
    },
    {
      "id": "n570",
      "time": 241500,
      "x": 2,
      "type": "hold",
      "durationMs": 1380
    },
    {
      "id": "n571",
      "time": 243000,
      "x": 2,
      "type": "hold",
      "durationMs": 2880
    },
    {
      "id": "n572",
      "time": 243500,
      "x": 3,
      "type": "tap"
    },
    {
      "id": "n573",
      "time": 243500,
      "x": 7,
      "type": "tap"
    },
    {
      "id": "n574",
      "time": 244000,
      "x": 3,
      "type": "tap"
    },
    {
      "id": "n575",
      "time": 244000,
      "x": 7,
      "type": "tap"
    },
    {
      "id": "n576",
      "time": 244500,
      "x": 7,
      "type": "tap"
    },
    {
      "id": "n577",
      "time": 245000,
      "x": 7,
      "type": "tap"
    },
    {
      "id": "n578",
      "time": 245500,
      "x": 7,
      "type": "tap"
    },
    {
      "id": "n579",
      "time": 246000,
      "x": 2,
      "type": "hold",
      "durationMs": 1500
    },
    {
      "id": "n580",
      "time": 246000,
      "x": 7,
      "type": "tap"
    },
    {
      "id": "n581",
      "time": 246500,
      "x": 7,
      "type": "tap"
    },
    {
      "id": "n582",
      "time": 247000,
      "x": 7,
      "type": "hold",
      "durationMs": 1000
    },
    {
      "id": "n583",
      "time": 247500,
      "x": 0,
      "type": "hold",
      "durationMs": 3000
    },
    {
      "id": "n584",
      "time": 248000,
      "x": 2,
      "type": "tap"
    },
    {
      "id": "n585",
      "time": 248000,
      "x": 6,
      "type": "tap"
    },
    {
      "id": "n586",
      "time": 248500,
      "x": 2,
      "type": "tap"
    },
    {
      "id": "n587",
      "time": 248500,
      "x": 7,
      "type": "tap"
    },
    {
      "id": "n588",
      "time": 249000,
      "x": 3,
      "type": "hold",
      "durationMs": 1500
    },
    {
      "id": "n589",
      "time": 249000,
      "x": 6,
      "type": "hold",
      "durationMs": 1500
    },
    {
      "id": "n590",
      "time": 250500,
      "x": 1,
      "type": "hold",
      "durationMs": 1380
    },
    {
      "id": "n591",
      "time": 250500,
      "x": 5,
      "type": "hold",
      "durationMs": 1500
    },
    {
      "id": "n592",
      "time": 252000,
      "x": 1,
      "type": "hold",
      "durationMs": 2880
    },
    {
      "id": "n593",
      "time": 252500,
      "x": 2,
      "type": "tap"
    },
    {
      "id": "n594",
      "time": 252500,
      "x": 6,
      "type": "tap"
    },
    {
      "id": "n595",
      "time": 253000,
      "x": 3,
      "type": "tap"
    },
    {
      "id": "n596",
      "time": 253000,
      "x": 6,
      "type": "tap"
    },
    {
      "id": "n597",
      "time": 253500,
      "x": 6,
      "type": "hold",
      "durationMs": 1380
    },
    {
      "id": "n598",
      "time": 254000,
      "x": 7,
      "type": "tap"
    },
    {
      "id": "n599",
      "time": 254500,
      "x": 7,
      "type": "tap"
    },
    {
      "id": "n600",
      "time": 255000,
      "x": 1,
      "type": "hold",
      "durationMs": 1380
    },
    {
      "id": "n601",
      "time": 255000,
      "x": 6,
      "type": "tap"
    },
    {
      "id": "n602",
      "time": 255500,
      "x": 7,
      "type": "tap"
    },
    {
      "id": "n603",
      "time": 256000,
      "x": 6,
      "type": "hold",
      "durationMs": 1000
    },
    {
      "id": "n604",
      "time": 256500,
      "x": 1,
      "type": "hold",
      "durationMs": 2880
    },
    {
      "id": "n605",
      "time": 257000,
      "x": 2,
      "type": "tap"
    },
    {
      "id": "n606",
      "time": 257000,
      "x": 5,
      "type": "tap"
    },
    {
      "id": "n607",
      "time": 257500,
      "x": 3,
      "type": "tap"
    },
    {
      "id": "n608",
      "time": 257500,
      "x": 6,
      "type": "tap"
    },
    {
      "id": "n609",
      "time": 258000,
      "x": 5,
      "type": "hold",
      "durationMs": 1380
    },
    {
      "id": "n610",
      "time": 259500,
      "x": 1,
      "type": "tap"
    },
    {
      "id": "n611",
      "time": 259500,
      "x": 5,
      "type": "hold",
      "durationMs": 1500
    },
    {
      "id": "n612",
      "time": 260250,
      "x": 0,
      "type": "tap"
    },
    {
      "id": "n613",
      "time": 261000,
      "x": 0,
      "type": "tap"
    },
    {
      "id": "n614",
      "time": 261500,
      "x": 4,
      "type": "hold",
      "durationMs": 1000
    },
    {
      "id": "n615",
      "time": 262000,
      "x": 3,
      "type": "hold",
      "durationMs": 3500
    },
    {
      "id": "n616",
      "time": 262500,
      "x": 2,
      "type": "hold",
      "durationMs": 3000
    },
    {
      "id": "n617",
      "time": 262500,
      "x": 7,
      "type": "hold",
      "durationMs": 1500
    },
    {
      "id": "n618",
      "time": 264000,
      "x": 6,
      "type": "hold",
      "durationMs": 2000
    },
    {
      "id": "n619",
      "time": 265500,
      "x": 0,
      "type": "hold",
      "durationMs": 3000
    },
    {
      "id": "n620",
      "time": 266000,
      "x": 1,
      "type": "hold",
      "durationMs": 4000
    },
    {
      "id": "n621",
      "time": 266000,
      "x": 5,
      "type": "hold",
      "durationMs": 4000
    },
    {
      "id": "n622",
      "time": 266500,
      "x": 7,
      "type": "tap"
    },
    {
      "id": "n623",
      "time": 267000,
      "x": 6,
      "type": "hold",
      "durationMs": 3500
    },
    {
      "id": "n624",
      "time": 270000,
      "x": 0,
      "type": "hold",
      "durationMs": 3000
    },
    {
      "id": "n625",
      "time": 270500,
      "x": 1,
      "type": "hold",
      "durationMs": 1000
    },
    {
      "id": "n626",
      "time": 270500,
      "x": 4,
      "type": "tap"
    },
    {
      "id": "n627",
      "time": 271000,
      "x": 4,
      "type": "tap"
    },
    {
      "id": "n628",
      "time": 271500,
      "x": 2,
      "type": "hold",
      "durationMs": 1380
    },
    {
      "id": "n629",
      "time": 271500,
      "x": 5,
      "type": "hold",
      "durationMs": 1500
    },
    {
      "id": "n630",
      "time": 273000,
      "x": 2,
      "type": "hold",
      "durationMs": 1500
    },
    {
      "id": "n631",
      "time": 273000,
      "x": 4,
      "type": "hold",
      "durationMs": 1500
    },
    {
      "id": "n632",
      "time": 274500,
      "x": 0,
      "type": "hold",
      "durationMs": 3000
    },
    {
      "id": "n633",
      "time": 275000,
      "x": 1,
      "type": "hold",
      "durationMs": 4000
    },
    {
      "id": "n634",
      "time": 275000,
      "x": 4,
      "type": "hold",
      "durationMs": 4000
    },
    {
      "id": "n635",
      "time": 275500,
      "x": 7,
      "type": "tap"
    },
    {
      "id": "n636",
      "time": 276000,
      "x": 6,
      "type": "hold",
      "durationMs": 1380
    },
    {
      "id": "n637",
      "time": 277500,
      "x": 2,
      "type": "hold",
      "durationMs": 1500
    },
    {
      "id": "n638",
      "time": 277500,
      "x": 6,
      "type": "hold",
      "durationMs": 1500
    },
    {
      "id": "n639",
      "time": 279000,
      "x": 0,
      "type": "hold",
      "durationMs": 4380
    },
    {
      "id": "n640",
      "time": 279500,
      "x": 4,
      "type": "tap"
    },
    {
      "id": "n641",
      "time": 280000,
      "x": 4,
      "type": "tap"
    },
    {
      "id": "n642",
      "time": 280500,
      "x": 4,
      "type": "hold",
      "durationMs": 1380
    },
    {
      "id": "n643",
      "time": 282000,
      "x": 4,
      "type": "hold",
      "durationMs": 1500
    },
    {
      "id": "n644",
      "time": 283500,
      "x": 0,
      "type": "hold",
      "durationMs": 1500
    },
    {
      "id": "n645",
      "time": 284000,
      "x": 4,
      "type": "hold",
      "durationMs": 1000
    },
    {
      "id": "n646",
      "time": 284500,
      "x": 5,
      "type": "tap"
    },
    {
      "id": "n647",
      "time": 285000,
      "x": 1,
      "type": "hold",
      "durationMs": 1500
    },
    {
      "id": "n648",
      "time": 285000,
      "x": 5,
      "type": "hold",
      "durationMs": 1500
    },
    {
      "id": "n649",
      "time": 286500,
      "x": 2,
      "type": "hold",
      "durationMs": 1500
    },
    {
      "id": "n650",
      "time": 286500,
      "x": 4,
      "type": "hold",
      "durationMs": 1500
    },
    {
      "id": "n651",
      "time": 288000,
      "x": 0,
      "type": "hold",
      "durationMs": 3000
    },
    {
      "id": "n652",
      "time": 288500,
      "x": 4,
      "type": "hold",
      "durationMs": 1000
    },
    {
      "id": "n653",
      "time": 288750,
      "x": 1,
      "type": "tap"
    },
    {
      "id": "n654",
      "time": 289000,
      "x": 6,
      "type": "tap"
    },
    {
      "id": "n655",
      "time": 289500,
      "x": 3,
      "type": "hold",
      "durationMs": 1500
    },
    {
      "id": "n656",
      "time": 289500,
      "x": 5,
      "type": "hold",
      "durationMs": 1500
    },
    {
      "id": "n657",
      "time": 291000,
      "x": 1,
      "type": "hold",
      "durationMs": 1500
    },
    {
      "id": "n658",
      "time": 291000,
      "x": 4,
      "type": "hold",
      "durationMs": 1500
    },
    {
      "id": "n659",
      "time": 292500,
      "x": 0,
      "type": "tap"
    },
    {
      "id": "n660",
      "time": 293000,
      "x": 0,
      "type": "tap"
    },
    {
      "id": "n661",
      "time": 293500,
      "x": 4,
      "type": "tap"
    },
    {
      "id": "n662",
      "time": 294000,
      "x": 0,
      "type": "hold",
      "durationMs": 1380
    },
    {
      "id": "n663",
      "time": 294500,
      "x": 1,
      "type": "tap"
    },
    {
      "id": "n664",
      "time": 294750,
      "x": 4,
      "type": "tap"
    },
    {
      "id": "n665",
      "time": 295250,
      "x": 4,
      "type": "tap"
    },
    {
      "id": "n666",
      "time": 295500,
      "x": 0,
      "type": "tap"
    },
    {
      "id": "n667",
      "time": 296000,
      "x": 0,
      "type": "tap"
    },
    {
      "id": "n668",
      "time": 296500,
      "x": 4,
      "type": "tap"
    },
    {
      "id": "n669",
      "time": 297000,
      "x": 0,
      "type": "hold",
      "durationMs": 1380
    },
    {
      "id": "n670",
      "time": 297500,
      "x": 1,
      "type": "tap"
    },
    {
      "id": "n671",
      "time": 297750,
      "x": 4,
      "type": "tap"
    },
    {
      "id": "n672",
      "time": 298250,
      "x": 4,
      "type": "tap"
    },
    {
      "id": "n673",
      "time": 298500,
      "x": 0,
      "type": "hold",
      "durationMs": 2880
    },
    {
      "id": "n674",
      "time": 299000,
      "x": 1,
      "type": "tap"
    },
    {
      "id": "n675",
      "time": 299500,
      "x": 2,
      "type": "tap"
    },
    {
      "id": "n676",
      "time": 300000,
      "x": 3,
      "type": "hold",
      "durationMs": 1500
    },
    {
      "id": "n677",
      "time": 300000,
      "x": 4,
      "type": "hold",
      "durationMs": 1500
    },
    {
      "id": "n678",
      "time": 301500,
      "x": 0,
      "type": "hold",
      "durationMs": 1500
    },
    {
      "id": "n679",
      "time": 302000,
      "x": 2,
      "type": "tap"
    },
    {
      "id": "n680",
      "time": 302500,
      "x": 5,
      "type": "tap"
    },
    {
      "id": "n681",
      "time": 303000,
      "x": 1,
      "type": "hold",
      "durationMs": 1500
    },
    {
      "id": "n682",
      "time": 303500,
      "x": 3,
      "type": "tap"
    },
    {
      "id": "n683",
      "time": 303750,
      "x": 5,
      "type": "tap"
    },
    {
      "id": "n684",
      "time": 304250,
      "x": 7,
      "type": "tap"
    },
    {
      "id": "n685",
      "time": 304500,
      "x": 0,
      "type": "hold",
      "durationMs": 1500
    },
    {
      "id": "n686",
      "time": 305000,
      "x": 2,
      "type": "tap"
    },
    {
      "id": "n687",
      "time": 305500,
      "x": 5,
      "type": "tap"
    },
    {
      "id": "n688",
      "time": 306000,
      "x": 1,
      "type": "hold",
      "durationMs": 1380
    },
    {
      "id": "n689",
      "time": 306500,
      "x": 3,
      "type": "tap"
    },
    {
      "id": "n690",
      "time": 306750,
      "x": 5,
      "type": "tap"
    },
    {
      "id": "n691",
      "time": 307250,
      "x": 7,
      "type": "tap"
    },
    {
      "id": "n692",
      "time": 307500,
      "x": 1,
      "type": "hold",
      "durationMs": 2880
    },
    {
      "id": "n693",
      "time": 308000,
      "x": 2,
      "type": "tap"
    },
    {
      "id": "n694",
      "time": 308500,
      "x": 3,
      "type": "tap"
    },
    {
      "id": "n695",
      "time": 309000,
      "x": 7,
      "type": "hold",
      "durationMs": 1380
    },
    {
      "id": "n696",
      "time": 310500,
      "x": 1,
      "type": "hold",
      "durationMs": 3000
    },
    {
      "id": "n697",
      "time": 310500,
      "x": 7,
      "type": "hold",
      "durationMs": 1380
    },
    {
      "id": "n698",
      "time": 311000,
      "x": 2,
      "type": "tap"
    },
    {
      "id": "n699",
      "time": 311500,
      "x": 3,
      "type": "tap"
    },
    {
      "id": "n700",
      "time": 312000,
      "x": 7,
      "type": "hold",
      "durationMs": 1380
    },
    {
      "id": "n701",
      "time": 313500,
      "x": 0,
      "type": "hold",
      "durationMs": 1380
    },
    {
      "id": "n702",
      "time": 313500,
      "x": 7,
      "type": "hold",
      "durationMs": 1380
    },
    {
      "id": "n703",
      "time": 315000,
      "x": 0,
      "type": "tap"
    },
    {
      "id": "n704",
      "time": 315000,
      "x": 7,
      "type": "hold",
      "durationMs": 4380
    },
    {
      "id": "n705",
      "time": 315500,
      "x": 0,
      "type": "tap"
    },
    {
      "id": "n706",
      "time": 316000,
      "x": 1,
      "type": "tap"
    },
    {
      "id": "n707",
      "time": 316500,
      "x": 3,
      "type": "tap"
    },
    {
      "id": "n708",
      "time": 317000,
      "x": 3,
      "type": "tap"
    },
    {
      "id": "n709",
      "time": 317500,
      "x": 3,
      "type": "tap"
    },
    {
      "id": "n710",
      "time": 318000,
      "x": 3,
      "type": "tap"
    },
    {
      "id": "n711",
      "time": 318500,
      "x": 3,
      "type": "tap"
    },
    {
      "id": "n712",
      "time": 319000,
      "x": 3,
      "type": "tap"
    },
    {
      "id": "n713",
      "time": 319500,
      "x": 2,
      "type": "hold",
      "durationMs": 3000
    },
    {
      "id": "n714",
      "time": 319500,
      "x": 7,
      "type": "hold",
      "durationMs": 3000
    }
  ]
}
